hdtable/__init__.py
hdtable/hdtable.py
hdtable/sphinx_ext.py
hdtable/utils.py
tests/__init__.py
tests/test_column.py
hdtable-0.1a5.dist-info/LICENSE
hdtable-0.1a5.dist-info/METADATA
hdtable-0.1a5.dist-info/WHEEL
hdtable-0.1a5.dist-info/entry_points.txt
hdtable-0.1a5.dist-info/top_level.txt
hdtable-0.1a5.dist-info/RECORD
