Metadata-Version: 2.1
Name: hdtable
Version: 0.1a5
Summary: Generate reStructuredText grid tables from hierarchical data
Home-page: https://gitlab.com/yagehu/hdtable
Author: Yage Hu
Author-email: yagejhu@gmail.com
License: UNKNOWN
Platform: UNKNOWN
Classifier: Development Status :: 3 - Alpha
Classifier: Programming Language :: Python :: 3.6
Classifier: Programming Language :: Python :: 3.7
Requires-Python: >=3.6
Requires-Dist: anytree (==2.4.3)
Requires-Dist: docutils (==0.14)
Requires-Dist: pyyaml (==4.2b4)
Requires-Dist: six (==1.11.0)
